reterm/__init__.py
reterm/cli.py
reterm/config.py
reterm/llm.py
reterm/shell.py
reterm/welcome.py
reterm_ai-0.1.2.dist-info/licenses/LICENSE
reterm_ai-0.1.2.dist-info/METADATA
reterm_ai-0.1.2.dist-info/WHEEL
reterm_ai-0.1.2.dist-info/entry_points.txt
reterm_ai-0.1.2.dist-info/top_level.txt
reterm_ai-0.1.2.dist-info/RECORD
