Metadata-Version: 2.4
Name: reterm-ai
Version: 0.1.2
Summary: AI-powered terminal command recommender based on your shell history
Home-page: https://github.com/pie0902/reTermAI
Author: pie0902
License: Apache-2.0
Classifier: Programming Language :: Python :: 3
Classifier: License :: OSI Approved :: Apache Software License
Classifier: Operating System :: OS Independent
Requires-Python: >=3.8
License-File: LICENSE
Requires-Dist: typer
Requires-Dist: python-dotenv
Requires-Dist: openai
Requires-Dist: google-generativeai
Dynamic: author
Dynamic: classifier
Dynamic: description
Dynamic: description-content-type
Dynamic: home-page
Dynamic: license
Dynamic: license-file
Dynamic: requires-dist
Dynamic: requires-python
Dynamic: summary
